LICENSE
README.md
setup.py
src/aws_cloudformation_power_switch/__init__.py
src/aws_cloudformation_power_switch/__main__.py
src/aws_cloudformation_power_switch/asg.py
src/aws_cloudformation_power_switch/ec2.py
src/aws_cloudformation_power_switch/ecs.py
src/aws_cloudformation_power_switch/lambda_handler.py
src/aws_cloudformation_power_switch/master.py
src/aws_cloudformation_power_switch/power_switch.py
src/aws_cloudformation_power_switch/rds.py
src/aws_cloudformation_power_switch/rds_cluster.py
src/aws_cloudformation_power_switch/tag.py
src/aws_cloudformation_power_switch.egg-info/PKG-INFO
src/aws_cloudformation_power_switch.egg-info/SOURCES.txt
src/aws_cloudformation_power_switch.egg-info/dependency_links.txt
src/aws_cloudformation_power_switch.egg-info/entry_points.txt
src/aws_cloudformation_power_switch.egg-info/not-zip-safe
src/aws_cloudformation_power_switch.egg-info/requires.txt
src/aws_cloudformation_power_switch.egg-info/top_level.txt