Metadata-Version: 2.1
Name: aws-cloudformation-power-switch
Version: 1.0.4
Summary: shutdown and startup AWS CloudFormation EC2 and RDS instances
Home-page: https://github.com/binxio/aws-cloudformation-power-switch
Author: Mark van Holsteijn
Author-email: mark@binx.io
License: BSD
Platform: any
Classifier: Development Status :: 4 - Beta
Classifier: Environment :: Console
Classifier: Intended Audience :: Developers
Classifier: License :: OSI Approved :: BSD License
Classifier: Operating System :: POSIX
Classifier: Operating System :: MacOS
Classifier: Operating System :: Unix
Classifier: Operating System :: Microsoft :: Windows
Classifier: Programming Language :: Python
Classifier: Programming Language :: Python :: 3
Classifier: Topic :: Software Development :: Libraries :: Python Modules
License-File: LICENSE
